plot_keras_history/__init__.py
plot_keras_history/__version__.py
plot_keras_history/plot_keras_history.py
plot_keras_history/utils.py
plot_keras_history-1.0.2.dist-info/LICENSE
plot_keras_history-1.0.2.dist-info/METADATA
plot_keras_history-1.0.2.dist-info/WHEEL
plot_keras_history-1.0.2.dist-info/top_level.txt
plot_keras_history-1.0.2.dist-info/RECORD
